[{"id":"1816376e-62f5-4982-b6be-5005a742577a","capacidadCombustible":100,"costoKm":150,"capacidadMaxPasajeros":100,"tarifa":3000,"velocidadMaxima":1000.0,"tipoPropulsion":"HELICE","servicioCatering":false,"actual":"BSAS","clase":"BRONZE","reservas":{"2020-11-20":"767d894c-8984-4031-9b35-a5dab0e5f2ca"}},{"id":"1bc16dcd-11e3-4a0d-aeec-3dc6c3844d3d","capacidadCombustible":250,"costoKm":250,"capacidadMaxPasajeros":50,"tarifa":4000,"velocidadMaxima":2000.0,"tipoPropulsion":"PISTON","servicioCatering":true,"actual":"CORDOBA","clase":"SILVER","reservas":{}},{"conexionWifi":true,"id":"5dff0558-53aa-4f6f-9eab-e2ae16dbebe8","capacidadCombustible":500,"costoKm":250,"capacidadMaxPasajeros":20,"tarifa":6000,"velocidadMaxima":3000.0,"tipoPropulsion":"REACCION","servicioCatering":true,"actual":"MONTEVIDEO","clase":"GOLD","reservas":{}},{"id":"480eb999-0bb9-408e-8062-7948ab8a92fa","capacidadCombustible":250,"costoKm":250,"capacidadMaxPasajeros":25,"tarifa":4000,"velocidadMaxima":2000.0,"tipoPropulsion":"PISTON","servicioCatering":true,"actual":"CORDOBA","clase":"SILVER","reservas":{}},{"conexionWifi":true,"id":"65a65b70-d588-4975-881a-db2c47992e65","capacidadCombustible":500,"costoKm":250,"capacidadMaxPasajeros":10,"tarifa":6000,"velocidadMaxima":3000.0,"tipoPropulsion":"REACCION","servicioCatering":true,"actual":"SANTIAGO","clase":"GOLD","reservas":{}}]