[{"id":"b2ea9b93-c412-4b08-9c28-bf2157a3719d","origen":"CORDOBA","destino":"BSAS","cantPasajeros":5,"avion":{"type":"Bronze","id":"dea423c9-71bc-4178-bd1f-317f32ccc40b","capacidadCombustible":100,"costoKm":150,"capacidadMaxPasajeros":100,"tarifa":3000,"velocidadMaxima":1000.0,"tipoPropulsion":"HELICE","servicioCatering":false,"actual":"BSAS","clase":"BRONZE","reservas":{}},"costoTotal":124750.0,"fecha":{"year":2020,"month":6,"day":10},"estado":1,"pasajeros":{},"clase":"SILVER"},{"id":"8e55ed36-ed86-474d-aa3c-be305098eb1e","origen":"BSAS","destino":"SANTIAGO","cantPasajeros":5,"avion":{"type":"Silver","id":"91faed00-f34c-4df5-9d4d-41e5da6c83c7","capacidadCombustible":250,"costoKm":250,"capacidadMaxPasajeros":50,"tarifa":4000,"velocidadMaxima":2000.0,"tipoPropulsion":"PISTON","servicioCatering":true,"actual":"SANTIAGO","clase":"SILVER","reservas":{}},"costoTotal":371500.0,"fecha":{"year":2020,"month":6,"day":11},"estado":1,"pasajeros":{},"clase":"BRONZE"}]